typer_verbose/__init__.py
typer_verbose-0.1.2.dist-info/licenses/LICENCE
typer_verbose-0.1.2.dist-info/WHEEL
typer_verbose-0.1.2.dist-info/METADATA
typer_verbose-0.1.2.dist-info/RECORD
